core_spec_pyscf-0.3.dist-info/licenses/LICENSE
pyscf/cvs/__init__.py
pyscf/cvs/ghf.py
pyscf/cvs/no_fxc.py
pyscf/cvs/rhf.py
pyscf/cvs/uhf.py
pyscf/cvs/test/test_core_syntax.py
pyscf/cvs/test/test_direct_diag.py
pyscf/cvs/test/test_no_fxc.py
pyscf/cvs/test/test_smoke.py
pyscf/cvs/test/test_tda-rpa.py
pyscf/cvs/test/test_trans_dip.py
pyscf/zora/ZORA.py
pyscf/zora/__init__.py
pyscf/zora/modbas2c.py
pyscf/zora/test/test_rhf.py
core_spec_pyscf-0.3.dist-info/METADATA
core_spec_pyscf-0.3.dist-info/WHEEL
core_spec_pyscf-0.3.dist-info/top_level.txt
core_spec_pyscf-0.3.dist-info/RECORD
