Metadata-Version: 2.4
Name: core-spec-pyscf
Version: 0.3
Summary: PySCF extension for easier access to core-level spectroscopy calculations
Author-email: Nathan Gillispie <nwgllspe@memphis.edu>
License-Expression: Apache-2.0
Project-URL: Homepage, https://github.com/NathanGillispie/core-spec-pyscf
Project-URL: Issues, https://github.com/NathanGillispie/core-spec-pyscf/issues
Classifier: Development Status :: 3 - Alpha
Classifier: Intended Audience :: Science/Research
Classifier: Topic :: Scientific/Engineering :: Chemistry
Classifier: Operating System :: POSIX
Classifier: Operating System :: Unix
Classifier: Operating System :: MacOS
Requires-Python: >=3.10
License-File: LICENSE
Dynamic: license-file
